bin/__init__.py
bin/itolparser_functions.py
itolparser-0.1.4.data/scripts/itolparser
itolparser_functions/__init__.py
itolparser_functions/itolparser_functions.py
itolparser-0.1.4.dist-info/LICENSE
itolparser-0.1.4.dist-info/METADATA
itolparser-0.1.4.dist-info/WHEEL
itolparser-0.1.4.dist-info/top_level.txt
itolparser-0.1.4.dist-info/RECORD
