Metadata-Version: 2.1
Name: itolparser
Version: 0.1.4
Summary: Small script to produce iTOL colorstrip metadata files from a table
Home-page: https://github.com/boasvdp/itolparser
Author: Boas van der Putten
Author-email: boas.vanderputten@amsterdamumc.nl
License: UNKNOWN
Platform: UNKNOWN
Classifier: Programming Language :: Python :: 3
Classifier: License :: OSI Approved :: MIT License
Classifier: Operating System :: OS Independent
Requires-Dist: colorbrewer
Requires-Dist: pandas
Requires-Dist: numpy
